newseyevent/__init__.py
newseyevent/solr.py
newseyevent-0.1.0.dev202101111736.dist-info/LICENSE
newseyevent-0.1.0.dev202101111736.dist-info/METADATA
newseyevent-0.1.0.dev202101111736.dist-info/WHEEL
newseyevent-0.1.0.dev202101111736.dist-info/top_level.txt
newseyevent-0.1.0.dev202101111736.dist-info/RECORD
