Metadata-Version: 2.1
Name: newseyevent
Version: 0.1.0.dev202101111736
Summary: A simple Python package to build event based requests for the NewsEye API
Home-page: https://gitlab.com/guilieb/newseyevent
Author: Guillaume Bernard
Author-email: contact@guillaume-bernard.fr
License: GPLv3 License
Platform: UNKNOWN
Classifier: License :: OSI Approved :: GNU General Public License v3 or later (GPLv3+)
Classifier: Intended Audience :: Developers
Classifier: Intended Audience :: Education
Classifier: Topic :: Scientific/Engineering :: Information Analysis
Classifier: Operating System :: OS Independent
Classifier: Programming Language :: Python
Classifier: Programming Language :: Python :: 3.7
Classifier: Programming Language :: Python :: 3.8
Requires-Dist: requests (==2.24.0)
Requires-Dist: wikivents
